[
  {      
    "id": "0707202101",
    "title": "Jurassic Park",
    "genre": "thriller",
    "imdb" : "6.5",
     "download": "http://www.google.com",
     "poster" : "https://cdn.europosters.eu/image/1300/posters/jurassic-park-i75969.jpg"
  },
  {     
    "id": "0707202102",
    "title": "Predator",
    "genre": "thriller",
    "imdb" : "6.5",
     "download": "http://www.google.com",
    "poster" : "https://cdn.shopify.com/s/files/1/0969/9128/products/Predator-ArnoldSchwarzenegger-HollywoodSciFiActionMovieFanArtGraphicPoster_04a1c614-bc54-4b0d-b878-9a7fc48bd8eb.jpg?v=1616064913"
  },
  {
  
    "id": "0707202103",
    "title": "Chathur Mukham",
    "genre": "horror",
    "imdb" : "2.5",
     "download": "https://www.pdisk.net/share-video?videoid=nv2fzh0008w3",
    "poster" : "https://encrypted-tbn0.gstatic.com/images?q=tbn:ANd9GcR25TnVV_FOnlOEFNYqKUVIrv_uYTOW9S_8XAUwrB9asVaug8TE"
  }
]
